README.rst
setup.py
flaskcap/__init__.py
flaskcap/app.py
flaskcap/log.py
flaskcap/orator.py
flaskcap/version.py
flaskcap.egg-info/PKG-INFO
flaskcap.egg-info/SOURCES.txt
flaskcap.egg-info/dependency_links.txt
flaskcap.egg-info/requires.txt
flaskcap.egg-info/top_level.txt